yt_dlpr/__init__.py
yt_dlpr/default_config.py
yt_dlpr/utils.py
yt_dlpr/yt_dlpr.py
yt_dlpr-1.3.dist-info/LICENSE
yt_dlpr-1.3.dist-info/METADATA
yt_dlpr-1.3.dist-info/WHEEL
yt_dlpr-1.3.dist-info/entry_points.txt
yt_dlpr-1.3.dist-info/top_level.txt
yt_dlpr-1.3.dist-info/RECORD
