Metadata-Version: 2.1
Name: yt-dlpr
Version: 1.3
Summary: Rich output of yt-dlp.
Home-page: https://github.com/Secozzi/yt-dlpr
Author: Folke
Author-email: folke.ishii@gmail.com
License: MIT license
Platform: UNKNOWN
Classifier: License :: OSI Approved :: MIT License
Classifier: Topic :: Multimedia :: Video
Classifier: Programming Language :: Python :: 3
Classifier: Programming Language :: Python :: 3.7
Classifier: Programming Language :: Python :: 3.8
Classifier: Programming Language :: Python :: 3.9
Classifier: Programming Language :: Python :: 3 :: Only
Requires-Dist: rich (>=9.4.0)
Requires-Dist: appdirs
Requires-Dist: yt-dlp
